LICENSE.txt
README.md
setup.py
testdroid/__init__.py
testdroid.egg-info/PKG-INFO
testdroid.egg-info/SOURCES.txt
testdroid.egg-info/dependency_links.txt
testdroid.egg-info/entry_points.txt
testdroid.egg-info/requires.txt
testdroid.egg-info/top_level.txt
testdroid.egg-info/zip-safe
testdroid/tests/__init__.py
testdroid/tests/test_all.py